soar_sami-0.2.2.data/scripts/reduce_sami
soar_sami-0.2.2.data/scripts/reduce_soi
soar_simager/__init__.py
soar_simager/data_reduction/__init__.py
soar_simager/data_reduction/combine.py
soar_simager/data_reduction/reduce.py
soar_simager/data_reduction/sami.py
soar_simager/data_reduction/sifs.py
soar_simager/data_reduction/soi.py
soar_simager/data_reduction/tests/__init__.py
soar_simager/data_reduction/tests/test_combine.py
soar_simager/data_reduction/tests/test_reduce.py
soar_simager/data_reduction/tests/test_sami.py
soar_simager/data_reduction/tests/test_soi.py
soar_simager/io/__init__.py
soar_simager/io/logging.py
soar_simager/io/tests/__init__.py
soar_simager/io/tests/test_logging.py
soar_simager/tools/__init__.py
soar_simager/tools/slices.py
soar_simager/tools/version.py
soar_simager/tools/tests/__init__.py
soar_simager/tools/tests/test_slices.py
soar_sami-0.2.2.dist-info/LICENSE
soar_sami-0.2.2.dist-info/METADATA
soar_sami-0.2.2.dist-info/WHEEL
soar_sami-0.2.2.dist-info/top_level.txt
soar_sami-0.2.2.dist-info/RECORD
